.gitignore
LICENSE
MANIFEST.in
NOTICES
README.rst
run_tests.sh
setup.py
loomengine_utils/.gitignore
loomengine_utils/VERSION
loomengine_utils/__init__.py
loomengine_utils/connection.py
loomengine_utils/exceptions.py
loomengine_utils/filemanager.py
loomengine_utils/md5calc.py
loomengine_utils/version.py
loomengine_utils.egg-info/PKG-INFO
loomengine_utils.egg-info/SOURCES.txt
loomengine_utils.egg-info/dependency_links.txt
loomengine_utils.egg-info/requires.txt
loomengine_utils.egg-info/top_level.txt
loomengine_utils/test/__init__.py
loomengine_utils/test/test_connection.py