Metadata-Version: 1.1
Name: loomengine-utils
Version: 0.6.0
Summary: loom workflow engine (utils)
Home-page: https://github.com/StanfordBioinformatics/loom
Author: Nathan Hammond
Author-email: info@loomengine.org
License: GNU Affero GPL
Keywords: bioinformatics pipeline runner workflow engine job scheduler
Platform: UNKNOWN
Classifier: Development Status :: 3 - Alpha
Classifier: Intended Audience :: Developers
Classifier: Intended Audience :: Science/Research
Classifier: Topic :: Scientific/Engineering :: Bio-Informatics
Classifier: Topic :: System :: Distributed Computing
Classifier: License :: OSI Approved :: GNU Affero General Public License v3 or later (AGPLv3+)
Classifier: Programming Language :: Python :: 2
Classifier: Programming Language :: Python :: 2.6
Classifier: Programming Language :: Python :: 2.7
